{
  "schoolCode": "TOPS10000T",
  "slug": "TOPS10000T",
  "name": "LS Alfieri",
  "canonicalName": "LS ALFIERI",
  "schoolLevelGroup": "secondaria-secondo-grado",
  "schoolTypeSlug": "liceo-scientifico",
  "schoolTypeLabel": "Liceo scientifico",
  "legalStatus": "statale",
  "publishedAt": "2026-04-08T00:00:00.000Z",
  "h1": "LS Alfieri a Torino: contatti, dati ufficiali e servizi",
  "metaTitle": "LS Alfieri a Torino | Contatti, servizi e dati ufficiali",
  "metaDescription": "Scheda scuola ufficiale per LS Alfieri a Torino: contatti, indirizzo, servizi, documenti e fonti MIM.",
  "regionSlug": "piemonte",
  "regionName": "Piemonte",
  "provinceSlug": "torino",
  "provinceName": "Torino",
  "provinceSigla": "TO",
  "citySlug": "torino",
  "cityName": "Torino",
  "address": {
    "street": "Corso Dante 80",
    "postalCode": "10126",
    "city": "Torino",
    "province": "TO",
    "region": "Piemonte",
    "full": "Corso Dante 80, 10126 Torino (TO)"
  },
  "coordinates": {"lat": 45.05, "lng": 7.68},
  "contacts": {
    "phone": "0116507594",
    "fax": null,
    "email": "tops10000t@istruzione.it",
    "pec": "tops10000t@pec.istruzione.it",
    "websiteUrl": null
  },
  "source": {
    "officialOverviewUrl": "https://unica.istruzione.gov.it/cercalatuascuola/istituti/TOPS10000T/ls-alfieri/",
    "didatticaUrl": "https://unica.istruzione.gov.it/cercalatuascuola/istituti/TOPS10000T/ls-alfieri/didattica/",
    "serviziUrl": "https://unica.istruzione.gov.it/cercalatuascuola/istituti/TOPS10000T/ls-alfieri/servizi/",
    "finanzaUrl": "https://unica.istruzione.gov.it/cercalatuascuola/istituti/TOPS10000T/ls-alfieri/finanza/",
    "ptofUrl": "https://unica.istruzione.gov.it/cercalatuascuola/istituti/TOPS10000T/ls-alfieri/ptof/",
    "ravUrl": "https://unica.istruzione.gov.it/cercalatuascuola/istituti/TOPS10000T/ls-alfieri/valutazione/",
    "rendicontazioneSocialeUrl": null,
    "ediliziaUrl": null,
    "ponUrl": null
  },
  "availability": {
    "hasDidattica": true,
    "hasServizi": true,
    "hasFinanza": true,
    "hasPtof": true,
    "hasRav": true,
    "hasRendicontazioneSociale": false,
    "hasEdilizia": false,
    "hasPon": false
  },
  "servicesSummary": null,
  "financeSummary": null,
  "documentsSummary": {"hasRav": true, "hasPtof": true, "hasRendicontazioneSociale": false},
  "nearbySchoolCodes": ["TOPS020006", "TOPC010003", "TOIC8A100T"],
  "sameTypeInCitySchoolCodes": ["TOPS020006"],
  "lastSourceCheckAt": "2026-04-08",
  "dataQuality": {"officiallyMatched": true, "matchMethod": "official-page-url", "missingFields": []}
}
